ty_command/__init__.py
ty_command/__main__.py
ty_command/ty.py
ty_command-2.0.1.dist-info/METADATA
ty_command-2.0.1.dist-info/WHEEL
ty_command-2.0.1.dist-info/entry_points.txt
ty_command-2.0.1.dist-info/licenses/LICENSE
ty_command-2.0.1.dist-info/RECORD
