Metadata-Version: 2.1
Name: ty-command
Version: 2.0.1
Summary: A configurable type-checking Python command
Project-URL: Homepage, https://github.com/yrom1/ty
Project-URL: Bug Tracker, https://github.com/yrom1/ty/issues
Author-email: Ryan Moore <ryanm.inbox@gmail.com>
License-File: LICENSE
Classifier: License :: OSI Approved :: MIT License
Classifier: Operating System :: OS Independent
Classifier: Programming Language :: Python :: 3
Requires-Python: >=3.10
Requires-Dist: mypy
Requires-Dist: pyright; platform_system != 'Windows'
Requires-Dist: pytype; platform_system != 'Windows'
Requires-Dist: tomli
